{
    "backend": "django",
    "db_name": "",
    "db_pass": "",
    "db_type": "mysql",
    "db_user": "",
    "dbms": "1",
    "description": "generated product",
    "design": "gradient-able",
    "docker": "0",
    "err_code": 0,
    "frontend": "",
    "heroku": "1",
    "pattern": "mvc",
    "pro": "0",
    "task_id": "2d6e3b2f-70ba-4928-8530-b1d285e703ec",
    "task_info": "Upload Sources [0%] - 143 files",
    "task_output": "2d6e3b2f-70ba-4928-8530-b1d285e703ec.zip",
    "task_result": "SUCCESS",
    "task_state": "RUNNING",
    "task_ts_end": "2022-07-17-09-36-31",
    "task_ts_start": "2022-07-17-09-36-30"
}